goog_stats/__init__.py
goog_stats/analyticsapi.py
goog_stats/consts.py
goog_stats-0.1.2.dist-info/WHEEL
goog_stats-0.1.2.dist-info/METADATA
goog_stats-0.1.2.dist-info/RECORD
