Metadata-Version: 2.1
Name: goog-stats
Version: 0.1.2
Summary: 
Author: Yash Jagdale
Author-email: jagdale0210@gmail.com
Requires-Python: >=3.8,<=3.10.8
Classifier: Programming Language :: Python :: 3
Classifier: Programming Language :: Python :: 3.8
Classifier: Programming Language :: Python :: 3.9
Classifier: Programming Language :: Python :: 3.10
Requires-Dist: logging (>=0.4.9.6,<0.5.0.0)
Requires-Dist: pathlib (>=1.0.1,<2.0.0)
Requires-Dist: pyyaml (>=6.0,<7.0)
Requires-Dist: requests (>=2.28.1,<3.0.0)
Requires-Dist: typer (>=0.4.0,<0.5.0)
